odoo/addons/project_scrum/README.rst
odoo/addons/project_scrum/__init__.py
odoo/addons/project_scrum/__manifest__.py
odoo/addons/project_scrum/data/ir_cron_data.xml
odoo/addons/project_scrum/i18n/it.po
odoo/addons/project_scrum/i18n/nl.po
odoo/addons/project_scrum/i18n/project_scrum.pot
odoo/addons/project_scrum/models/__init__.py
odoo/addons/project_scrum/models/project.py
odoo/addons/project_scrum/models/project_sprint.py
odoo/addons/project_scrum/models/project_task.py
odoo/addons/project_scrum/readme/CONTRIBUTORS.md
odoo/addons/project_scrum/readme/DESCRIPTION.md
odoo/addons/project_scrum/readme/USAGE.md
odoo/addons/project_scrum/security/ir.model.access.csv
odoo/addons/project_scrum/static/description/icon.png
odoo/addons/project_scrum/static/description/index.html
odoo/addons/project_scrum/tests/__init__.py
odoo/addons/project_scrum/tests/test_project_project.py
odoo/addons/project_scrum/tests/test_project_sprint.py
odoo/addons/project_scrum/tests/test_project_task.py
odoo/addons/project_scrum/views/project_sprint_views.xml
odoo/addons/project_scrum/views/project_task_views.xml
odoo/addons/project_scrum/views/project_views.xml
odoo_addon_project_scrum-18.0.1.0.0.5.dist-info/METADATA
odoo_addon_project_scrum-18.0.1.0.0.5.dist-info/WHEEL
odoo_addon_project_scrum-18.0.1.0.0.5.dist-info/top_level.txt
odoo_addon_project_scrum-18.0.1.0.0.5.dist-info/RECORD
