Metadata-Version: 2.1
Name: odoo-addon-project_scrum
Version: 18.0.1.0.0.5
Requires-Python: >=3.10
Requires-Dist: odoo-addon-project_timeline==18.0.*
Requires-Dist: odoo==18.0.*
Summary: This addon allow use the scrum methodology in projects
Home-page: https://github.com/OCA/project
License: AGPL-3
Author: Binhex, Odoo Community Association (OCA)
Author-email: support@odoo-community.org
Classifier: Programming Language :: Python
Classifier: Framework :: Odoo
Classifier: Framework :: Odoo :: 18.0
Classifier: License :: OSI Approved :: GNU Affero General Public License v3
